__init__.py
fmconsult/__init__.py
fmconsult/auth/__init__.py
fmconsult/auth/decorator.py
fmconsult/auth/profile_builder.py
fmconsult/auth/token_manager.py
fmconsult/database/__init__.py
fmconsult/database/connection.py
fmconsult/database/models/__init__.py
fmconsult/database/models/application.py
fmconsult/database/models/base.py
fmconsult/database/models/city.py
fmconsult/database/models/country.py
fmconsult/database/models/state.py
fmconsult/decorators/__init__.py
fmconsult/decorators/auth.py
fmconsult/exceptions/__init__.py
fmconsult/exceptions/authorization.py
fmconsult/exceptions/bad_request_exception.py
fmconsult/exceptions/conflict_exception.py
fmconsult/exceptions/forbidden_exception.py
fmconsult/exceptions/not_found_exception.py
fmconsult/exceptions/not_implemented_exception.py
fmconsult/exceptions/unauthorized_exception.py
fmconsult/exceptions/unavailable_exception.py
fmconsult/http/__init__.py
fmconsult/http/api.py
fmconsult/utils/__init__.py
fmconsult/utils/cast.py
fmconsult/utils/cnpj.py
fmconsult/utils/configs.py
fmconsult/utils/cpf.py
fmconsult/utils/date.py
fmconsult/utils/enum.py
fmconsult/utils/haversine.py
fmconsult/utils/object.py
fmconsult/utils/pagination.py
fmconsult/utils/string.py
fmconsult/utils/url.py
fmconsult_utils_python_sdk-2.0.12.dist-info/licenses/LICENSE
fmconsult_utils_python_sdk-2.0.12.dist-info/METADATA
fmconsult_utils_python_sdk-2.0.12.dist-info/WHEEL
fmconsult_utils_python_sdk-2.0.12.dist-info/top_level.txt
fmconsult_utils_python_sdk-2.0.12.dist-info/RECORD
