Metadata-Version: 2.4
Name: fmconsult-utils-python-sdk
Version: 2.0.12
Summary: Canivete suiço da FMConsult
Author-email: Filipe Coelho <filipe@fmconsult.com.br>
License: MIT License
Project-URL: Homepage, https://github.com/seuuser/minha-biblioteca
Project-URL: Bug Tracker, https://github.com/seuuser/minha-biblioteca/issues
Keywords: sdk,api,fmconsult
Classifier: Programming Language :: Python :: 3
Classifier: License :: OSI Approved :: MIT License
Classifier: Operating System :: OS Independent
Requires-Python: >=3.11
License-File: LICENSE
Dynamic: license-file
